{
  "name": "DHT sensor library",
  "version": "1.4.6,
  "keywords": "Arduino library for DHT11, DHT 11A, DHT 21, DHT22, etc Temp & Humidity Sensors",
  "description": "Arduino library for DHT11, DHT 11A, DHT 21, DHT22, etc Temp & Humidity Sensors.",
  "repository": {
    "type": "git",
    "url": "https://github.com/adafruit/DHT-sensor-library"
  },
  "authors": [{
    "name": "DNC",
    "email": "dncx@dnc.com.pl"
  }],
  "frameworks": "arduino",
  "platforms": "espressif32, espressif8266, atmelsam, atmelavr, atmelmegaavr, ststm32, teensy, rp2040"
}
